okra/__init__.py
okra/auth.py
okra/balance.py
okra/entry.py
okra/identity.py
okra/income.py
okra/okra_base.py
okra/records.py
okra/transactions.py
okra/utils.py
pyokra_houdini10-0.0.0.dist-info/LICENSE
pyokra_houdini10-0.0.0.dist-info/METADATA
pyokra_houdini10-0.0.0.dist-info/WHEEL
pyokra_houdini10-0.0.0.dist-info/top_level.txt
pyokra_houdini10-0.0.0.dist-info/RECORD
