Metadata-Version: 2.1
Name: pyokra-houdini10
Version: 0.0.0
Summary: A Python plugin for the okra API
Home-page: https://github.com/NonsoAmadi10/Okra.git
Author: Houdini10
Author-email: nonsoamadi@aol.com
License: UNKNOWN
Platform: UNKNOWN
Classifier: Programming Language :: Python :: 3
Classifier: License :: OSI Approved :: MIT License
Classifier: Operating System :: OS Independent
Requires-Python: >=3.6
